valempas/__init__.py
valempas-2.0.dist-info/METADATA
valempas-2.0.dist-info/WHEEL
valempas-2.0.dist-info/top_level.txt
valempas-2.0.dist-info/RECORD
