Metadata-Version: 2.4
Name: valempas
Version: 2.0
Summary: Library sederhana untuk validasi email dan password
Author-email: Rifki Taufikurrohman <rifkitmn23@gmail.com>
License: MIT
Project-URL: Homepage, https://github.com/rifkitaufikurrohman/valempas
Classifier: Programming Language :: Python :: 3
Classifier: License :: OSI Approved :: MIT License
Classifier: Operating System :: OS Independent
